robustsp/__init__.py
robustsp/AuxiliaryFunctions/SoftThresh.py
robustsp/AuxiliaryFunctions/__init__.py
robustsp/AuxiliaryFunctions/madn.py
robustsp/AuxiliaryFunctions/propform.py
robustsp/AuxiliaryFunctions/psihub.py
robustsp/AuxiliaryFunctions/rhohub.py
robustsp/AuxiliaryFunctions/rhotuk.py
robustsp/AuxiliaryFunctions/whub.py
robustsp/AuxiliaryFunctions/wtuk.py
robustsp/Covariance/Mscat.py
robustsp/Covariance/__init__.py
robustsp/Covariance/signcm.py
robustsp/Covariance/spatmed.py
robustsp/DependentData/__init__.py
robustsp/DependentData/ar_est_bip_s.py
robustsp/DependentData/ar_est_bip_tau.py
robustsp/DependentData/arma_est_bip_m.py
robustsp/DependentData/arma_est_bip_mm.py
robustsp/DependentData/arma_est_bip_s.py
robustsp/DependentData/arma_est_bip_tau.py
robustsp/DependentData/robust_starting_point.py
robustsp/DependentData/Auxiliary/__init__.py
robustsp/DependentData/Auxiliary/arma_resid.py
robustsp/DependentData/Auxiliary/arma_s_resid.py
robustsp/DependentData/Auxiliary/arma_s_resid_sc.py
robustsp/DependentData/Auxiliary/arma_tau_resid_sc.py
robustsp/DependentData/Auxiliary/bip_ar1_s.py
robustsp/DependentData/Auxiliary/bip_ar1_tau.py
robustsp/DependentData/Auxiliary/bip_resid.py
robustsp/DependentData/Auxiliary/bip_s_resid.py
robustsp/DependentData/Auxiliary/bip_s_resid_sc.py
robustsp/DependentData/Auxiliary/bip_tau_resid_sc.py
robustsp/DependentData/Auxiliary/eta.py
robustsp/DependentData/Auxiliary/helper.py
robustsp/DependentData/Auxiliary/m_scale.py
robustsp/DependentData/Auxiliary/ma_infinity.py
robustsp/DependentData/Auxiliary/muler_rho1.py
robustsp/DependentData/Auxiliary/muler_rho2.py
robustsp/DependentData/Auxiliary/tau_scale.py
robustsp/LocationScale/MLocHub.py
robustsp/LocationScale/MLocTuk.py
robustsp/LocationScale/MscaleHUB.py
robustsp/LocationScale/MscaleTUK.py
robustsp/LocationScale/__init__.py
robustsp/LocationScale/examples/__init__.py
robustsp/LocationScale/examples/sensitivity_curve_location.py
robustsp-0.1.1.dist-info/LICENSE.txt
robustsp-0.1.1.dist-info/METADATA
robustsp-0.1.1.dist-info/WHEEL
robustsp-0.1.1.dist-info/top_level.txt
robustsp-0.1.1.dist-info/RECORD
